gamenacki/__init__.py
gamenacki/common/__init__.py
gamenacki/common/base_constants.py
gamenacki/common/base_engine.py
gamenacki/common/base_game_state.py
gamenacki/common/base_player.py
gamenacki/common/base_renderer.py
gamenacki/common/dealer.py
gamenacki/common/log.py
gamenacki/common/piles.py
gamenacki/common/scorer.py
gamenacki/common/stack.py
gamenacki/lostcitinacki/__init__.py
gamenacki/lostcitinacki/engine.py
gamenacki/lostcitinacki/players.py
gamenacki/lostcitinacki/renderers.py
gamenacki/lostcitinacki/models/__init__.py
gamenacki/lostcitinacki/models/cards.py
gamenacki/lostcitinacki/models/constants.py
gamenacki/lostcitinacki/models/game_state.py
gamenacki/lostcitinacki/models/piles.py
gamenacki-0.1.1.dist-info/METADATA
gamenacki-0.1.1.dist-info/WHEEL
gamenacki-0.1.1.dist-info/RECORD
