Metadata-Version: 2.4
Name: gamenacki
Version: 0.1.1
Summary: library for games
Author-email: Bernacki <bernackimark@gmail.com>
License: MIT
